__init__.py
repo_ast_builder/__init__.py
repo_ast_builder/body.py
repo_ast_builder/main.py
repo_ast_builder/method_name.py
repo_ast_builder/namespace.py
repo_ast_builder/walk.py
repo_ast_builder/pycg/__init__.py
repo_ast_builder/pycg/__main__.py
repo_ast_builder/pycg/pycg.py
repo_ast_builder/pycg/formats/__init__.py
repo_ast_builder/pycg/formats/as_graph.py
repo_ast_builder/pycg/formats/base.py
repo_ast_builder/pycg/formats/fasten.py
repo_ast_builder/pycg/formats/simple.py
repo_ast_builder/pycg/machinery/__init__.py
repo_ast_builder/pycg/machinery/callgraph.py
repo_ast_builder/pycg/machinery/classes.py
repo_ast_builder/pycg/machinery/definitions.py
repo_ast_builder/pycg/machinery/imports.py
repo_ast_builder/pycg/machinery/key_err.py
repo_ast_builder/pycg/machinery/modules.py
repo_ast_builder/pycg/machinery/pointers.py
repo_ast_builder/pycg/machinery/scopes.py
repo_ast_builder/pycg/processing/__init__.py
repo_ast_builder/pycg/processing/base.py
repo_ast_builder/pycg/processing/cgprocessor.py
repo_ast_builder/pycg/processing/keyerrprocessor.py
repo_ast_builder/pycg/processing/postprocessor.py
repo_ast_builder/pycg/processing/preprocessor.py
repo_ast_builder/pycg/tests/base.py
repo_ast_builder/pycg/tests/callgraph_test.py
repo_ast_builder/pycg/tests/definitions_test.py
repo_ast_builder/pycg/tests/fasten_format_test.py
repo_ast_builder/pycg/tests/imports_test.py
repo_ast_builder/pycg/tests/pointers_test.py
repo_ast_builder/pycg/tests/scopes_test.py
repo_ast_builder/pycg/utils/__init__.py
repo_ast_builder/pycg/utils/common.py
repo_ast_builder/pycg/utils/constants.py
repo_ast_builder-0.0.9.dist-info/METADATA
repo_ast_builder-0.0.9.dist-info/WHEEL
repo_ast_builder-0.0.9.dist-info/entry_points.txt
repo_ast_builder-0.0.9.dist-info/top_level.txt
repo_ast_builder-0.0.9.dist-info/RECORD
